LICENSE
MANIFEST.in
README.md
setup.py
bee_data_cleaning/__init__.py
bee_data_cleaning/data_cleaning.py
bee_data_cleaning/utils.py
bee_data_cleaning/visualization.py
bee_data_cleaning.egg-info/PKG-INFO
bee_data_cleaning.egg-info/SOURCES.txt
bee_data_cleaning.egg-info/dependency_links.txt
bee_data_cleaning.egg-info/requires.txt
bee_data_cleaning.egg-info/top_level.txt
bee_data_cleaning/tests/__init__.py
bee_data_cleaning/tests/data_cleaning_test.py