Metadata-Version: 1.0
Name: bee-data-cleaning
Version: 0.0.2
Summary: Data cleaning for building energy and temperature timeseries.
Home-page: https://github.com/BeeGroup-cimne/bee_data_cleaning
Author: BEE Group - CIMNE
Author-email: egabaldon@cimne.upc.edu
License: MIT
Platform: UNKNOWN
